MANIFEST.in
README.markdown
setup.py
pingpong/__init__.py
pingpong/email.py
pingpong/models.py
pingpong/signals.py
pingpong/utils.py
pingpong.egg-info/PKG-INFO
pingpong.egg-info/SOURCES.txt
pingpong.egg-info/dependency_links.txt
pingpong.egg-info/requires.txt
pingpong.egg-info/top_level.txt
pingpong/management/__init__.py
pingpong/management/commands/__init__.py
pingpong/management/commands/pong.py