Metadata-Version: 1.0
Name: pingpong
Version: 0.0.1
Summary: Django library that makes triggering emails easier
Home-page: UNKNOWN
Author: James Robert
Author-email: jiaaro@gmail.com
License: MIT
Keywords: django
Platform: UNKNOWN
Classifier: Development Status :: 4 - Beta
Classifier: License :: OSI Approved :: MIT License
Classifier: Programming Language :: Python
Classifier: Framework :: Django
Classifier: Environment :: Web Environment
Classifier: Intended Audience :: Developers
Classifier: Operating System :: OS Independent
Classifier: Topic :: Internet :: WWW/HTTP
Classifier: Topic :: Utilities
